mlsql_plugin_tool-0.1.6.dist-info/DESCRIPTION.rst
mlsql_plugin_tool-0.1.6.dist-info/METADATA
mlsql_plugin_tool-0.1.6.dist-info/RECORD
mlsql_plugin_tool-0.1.6.dist-info/WHEEL
mlsql_plugin_tool-0.1.6.dist-info/entry_points.txt
mlsql_plugin_tool-0.1.6.dist-info/metadata.json
mlsql_plugin_tool-0.1.6.dist-info/top_level.txt
tech/__init__.py
tech/mlsql/__init__.py
tech/mlsql/plugin/__init__.py
tech/mlsql/plugin/tool/Plugin.py
tech/mlsql/plugin/tool/__init__.py
tech/mlsql/plugin/tool/http_manager.py
tech/mlsql/plugin/tool/shellutils.py
tech/mlsql/plugin/tool/commands/__init__.py
tech/mlsql/plugin/tool/commands/builder.py
tech/mlsql/plugin/tool/commands/compile_process.py
